voc/LICENSE
voc/README.md
voc/__init__.py
voc/c3data.py
voc/event.py
voc/generic.py
voc/git.py
voc/logger.py
voc/pretalx.py
voc/rc3hub.py
voc/room.py
voc/schedule.py
voc/tools.py
voc/voctoimport.py
voc/webcal.py
voc/webcal2.py
c3voc_schedule_tools-1.1.0.dist-info/METADATA
c3voc_schedule_tools-1.1.0.dist-info/WHEEL
c3voc_schedule_tools-1.1.0.dist-info/licenses/LICENCE.txt
c3voc_schedule_tools-1.1.0.dist-info/RECORD
